HW1-3/1-CR_Adder/adder_gate.v
module adder_gate(x, y, carry, out);
    input [7:0] x, y;
    output carry;
    output [7:0] out;

    /*Write your code here*/
    reg Cin=0;
    wire c1,c2,c3,c4,c5,c6,c7;
    full_adder A1(out[0],x[0],y[0],Cin,c1);
    full_adder A2(out[1],x[1],y[1],c1,c2);
    full_adder A3(out[2],x[2],y[2],c2,c3);
    full_adder A4(out[3],x[3],y[3],c3,c4);
    full_adder A5(out[4],x[4],y[4],c4,c5);
    full_adder A6(out[5],x[5],y[5],c5,c6);
    full_adder A7(out[6],x[6],y[6],c6,c7);
    full_adder A8(out[7],x[7],y[7],c7,carry);


    /*End of code*/
endmodule

module full_adder(co1,x1,y1,ci1,sum1);
    input x1,y1,ci1;
    output co1,sum1;
    wire w1,w2,w3;
    xor xor1( w1, x1, y1 );
    and and1( w2, w1, ci1 );
    and and2( w3, x1, y1 );
    xor xor2( sum1, w1, ci1 );
    or  or1( co1, w2, w3 );

endmodule

HW1-3/1-CR_Adder/adder_gate_test.v
`timescale 1ns/10ps
`define CYCLE 10.0
`define INFILE "in.pattern"
`define OUTFILE "out_golden.pattern" 

module adder_gate_test;
parameter pattern_num = 10;
wire [7:0] out;
wire carry;
reg [7:0] x, y;
reg  clk;
reg  stop;
integer i, num, error;

reg [8:0] ans_out;
reg [8:0] adder_out;

reg [7:0] data_base1 [0:100];
reg [8:0] data_base2 [0:100];

adder_gate A (x, y, carry, out);

initial begin
	$readmemh(`INFILE  , data_base1);
	$readmemh(`OUTFILE , data_base2);
	clk = 1'b1;
	error = 0;
	stop = 0;
	i=0;
end

always begin #(`CYCLE * 0.5) clk = ~clk;
end

initial begin
	x[7:0] = data_base1[0];
	y[7:0] = data_base1[1];
	
	for(num = 2; num < (pattern_num * 2); num = num + 2) begin
		@(posedge clk) begin
			x[7:0] = data_base1[num];
			y[7:0] = data_base1[num + 1];
		end
	end
end


always@(posedge clk) begin
	i <= i + 1;
	if (i >= pattern_num)
		stop <= 1;
end

always@(posedge clk ) begin
	adder_out <= {carry, out};
	ans_out <= data_base2[i];
	if(adder_out !== ans_out) begin
		error <= error + 1;
		$display("An ERROR occurs at no.%d pattern: {carry out, output} %h != answer %h.\n", i, adder_out, ans_out);
	end
end

initial begin
	@(posedge stop) begin
		if(error == 0) begin
			$display("==========================================\n");
			$display("======  Congratulation! You Pass!  =======\n");
			$display("==========================================\n");
		end
		else begin
			$display("===============================\n");
			$display("There are %d errors.", error);
			$display("===============================\n");
		end
		$finish;
	end
end

/*================Dumping Waveform files====================*/
initial begin
$dumpfile("adder.vcd");
$dumpvars;
/* 	$fsdbDumpfile("adder.fsdb");
	$fsdbDumpvars;  */
end

endmodule

HW1-3/1-CR_Adder/adder.vcd
$date
    Mar 29, 2018  17:12:16
$end
$version
    TOOL:	ncsim	10.20-s114
$end
$timescale
    10 ps
$end

$scope module adder_gate_test $end
$var parameter 32 !    pattern_num  $end
$var wire      1 "    out [7] $end
$var wire      1 #    out [6] $end
$var wire      1 $    out [5] $end
$var wire      1 %    out [4] $end
$var wire      1 &    out [3] $end
$var wire      1 '    out [2] $end
$var wire      1 (    out [1] $end
$var wire      1 )    out [0] $end
$var wire      1 *    carry  $end
$var reg       8 +    x [7:0] $end
$var reg       8 ,    y [7:0] $end
$var reg       1 -    clk  $end
$var reg       1 .    stop  $end
$var integer  32 /    i  $end
$var integer  32 0    num  $end
$var integer  32 1    error  $end
$var reg       9 2    ans_out [8:0] $end
$var reg       9 3    adder_out [8:0] $end

$scope module A $end
$var wire      1 4    x [7] $end
$var wire      1 5    x [6] $end
$var wire      1 6    x [5] $end
$var wire      1 7    x [4] $end
$var wire      1 8    x [3] $end
$var wire      1 9    x [2] $end
$var wire      1 :    x [1] $end
$var wire      1 ;    x [0] $end
$var wire      1 <    y [7] $end
$var wire      1 =    y [6] $end
$var wire      1 >    y [5] $end
$var wire      1 ?    y [4] $end
$var wire      1 @    y [3] $end
$var wire      1 A    y [2] $end
$var wire      1 B    y [1] $end
$var wire      1 C    y [0] $end
$var wire      1 *    carry  $end
$var wire      1 "    out [7] $end
$var wire      1 #    out [6] $end
$var wire      1 $    out [5] $end
$var wire      1 %    out [4] $end
$var wire      1 &    out [3] $end
$var wire      1 '    out [2] $end
$var wire      1 (    out [1] $end
$var wire      1 )    out [0] $end
$var reg       1 D    Cin  $end
$var wire      1 E    c1  $end
$var wire      1 F    c2  $end
$var wire      1 G    c3  $end
$var wire      1 H    c4  $end
$var wire      1 I    c5  $end
$var wire      1 J    c6  $end
$var wire      1 K    c7  $end

$scope module A1 $end
$var wire      1 ;    x1  $end
$var wire      1 C    y1  $end
$var wire      1 L    ci1  $end
$var wire      1 E    co1  $end
$var wire      1 )    sum1  $end
$var wire      1 M    w1  $end
$var wire      1 N    w2  $end
$var wire      1 O    w3  $end
$upscope $end


$scope module A2 $end
$var wire      1 :    x1  $end
$var wire      1 B    y1  $end
$var wire      1 E    ci1  $end
$var wire      1 F    co1  $end
$var wire      1 (    sum1  $end
$var wire      1 P    w1  $end
$var wire      1 Q    w2  $end
$var wire      1 R    w3  $end
$upscope $end


$scope module A3 $end
$var wire      1 9    x1  $end
$var wire      1 A    y1  $end
$var wire      1 F    ci1  $end
$var wire      1 G    co1  $end
$var wire      1 '    sum1  $end
$var wire      1 S    w1  $end
$var wire      1 T    w2  $end
$var wire      1 U    w3  $end
$upscope $end


$scope module A4 $end
$var wire      1 8    x1  $end
$var wire      1 @    y1  $end
$var wire      1 G    ci1  $end
$var wire      1 H    co1  $end
$var wire      1 &    sum1  $end
$var wire      1 V    w1  $end
$var wire      1 W    w2  $end
$var wire      1 X    w3  $end
$upscope $end


$scope module A5 $end
$var wire      1 7    x1  $end
$var wire      1 ?    y1  $end
$var wire      1 H    ci1  $end
$var wire      1 I    co1  $end
$var wire      1 %    sum1  $end
$var wire      1 Y    w1  $end
$var wire      1 Z    w2  $end
$var wire      1 [    w3  $end
$upscope $end


$scope module A6 $end
$var wire      1 6    x1  $end
$var wire      1 >    y1  $end
$var wire      1 I    ci1  $end
$var wire      1 J    co1  $end
$var wire      1 $    sum1  $end
$var wire      1 \    w1  $end
$var wire      1 ]    w2  $end
$var wire      1 ^    w3  $end
$upscope $end


$scope module A7 $end
$var wire      1 5    x1  $end
$var wire      1 =    y1  $end
$var wire      1 J    ci1  $end
$var wire      1 K    co1  $end
$var wire      1 #    sum1  $end
$var wire      1 _    w1  $end
$var wire      1 `    w2  $end
$var wire      1 a    w3  $end
$upscope $end


$scope module A8 $end
$var wire      1 4    x1  $end
$var wire      1 <    y1  $end
$var wire      1 K    ci1  $end
$var wire      1 *    co1  $end
$var wire      1 "    sum1  $end
$var wire      1 b    w1  $end
$var wire      1 c    w2  $end
$var wire      1 d    w3  $end
$upscope $end

$upscope $end

$upscope $end

$enddefinitions $end
$dumpvars
b1010 !
x"
x#
x$
x%
x&
x'
x(
x)
x*
b0 +
b0 ,
1-
0.
b0 /
b10 0
b0 1
bx 2
bx 3
04
05
06
07
08
09
0:
0;
0<
0=
0>
0?
0@
0A
0B
0C
0D
xE
xF
xG
xH
xI
xJ
xK
0L
xM
xN
xO
xP
xQ
xR
xS
xT
xU
xV
xW
xX
xY
xZ
x[
x\
x]
x^
x_
x`
xa
xb
xc
xd
$end
#100
0N
0M
0P
0S
0V
0Y
0\
0_
0b
0O
0R
0U
0X
0[
0^
0a
0d
#200
0E
0c
0`
0]
0Z
0W
0T
0Q
0)
#300
0F
0G
0H
0I
0J
0K
0*
0(
#400
0"
0#
0$
0%
0&
0'
#800
0-
#1600
1-
b11111111 +
b11111111 ,
b100 0
1<
1=
1>
1?
1@
1A
1B
1C
14
15
16
17
18
19
1:
1;
b1 /
b0 3
b0 2
#1700
1O
1R
1U
1X
1[
1^
1a
1d
#1800
1*
1K
1J
1I
1H
1G
1F
1E
#1900
1(
1'
1&
1%
1$
1#
1"
#2400
0-
#3200
1-
b101010 +
b11011000 ,
b110 0
0>
0A
0B
0C
04
05
07
09
0;
b10 /
b111111110 3
b111111110 2
#3300
1Y
0[
1_
0a
1b
0d
0O
1P
0R
0U
1\
0^
#3400
0J
0$
1]
0G
0F
0(
1Q
0E
0*
0"
1c
0K
0I
0%
1Z
#3500
1I
1"
0c
1(
0Q
0'
0&
1J
#3600
0#
1`
#3700
1K
#3800
0"
1c
#3900
1*
#4000
0-
#4800
1-
b111000 +
b111001 ,
b1000 0
0<
0=
1>
1C
17
0:
b11 /
b100000010 3
b100000010 2
#4900
0P
0Y
1[
1M
0\
1^
0_
0b
#5000
1"
0c
1#
0`
1$
0]
1)
1%
0Z
0(
#5100
0K
0*
#5200
0"
#5600
0-
#6400
1-
b1110000 +
b1111 ,
b1010 0
0>
0?
1A
1B
15
08
b100 /
b1110001 3
b1110001 2
#6500
1V
0X
1_
1P
1S
1Y
0[
1\
0^
#6600
0J
0$
1]
0I
0%
1Z
1'
1(
0H
1&
#6700
1%
0Z
1$
0]
#7200
0-
#8000
1-
b11001001 +
b11110 ,
b1100 0
1?
0C
14
06
07
18
1;
b101 /
b1111111 3
b1111111 2
#8100
0V
1X
0\
1b
#8200
1"
0$
1H
0&
#8300
0%
1Z
#8400
1I
#8500
1$
#8800
0-
#9600
1-
b1011011 +
b1101010 ,
b1110 0
1=
1>
0?
0A
04
17
1:
b110 /
b11100111 3
b11100111 2
#9700
0P
1R
0b
0S
1\
0_
1a
#9800
1K
0#
0$
1]
0'
1F
0(
#9900
1'
1J
#10000
1#
#10400
0-
#11200
1-
b11101 +
b11010001 ,
b10000 0
1<
0>
1?
0@
0B
1C
05
19
0:
b111 /
b11000101 3
b11000101 2
#11300
1S
1_
0a
0M
1O
0R
1V
0X
0Y
1[
0\
1b
#11400
0"
1c
1$
0]
1%
0Z
0H
1&
0F
1E
0)
0K
0#
1`
#11500
1K
1(
0%
0J
1*
#11600
1#
0`
#11700
0K
#11800
1"
0c
#11900
0*
#12000
0-
#12800
1-
b11101001 +
b11111000 ,
b10010 0
1>
1@
0C
14
15
16
07
09
b1000 /
b11101110 3
b11101110 2
#12900
0S
1Y
0[
1^
0_
1a
0b
1d
1M
0O
0V
1X
#13000
1H
0&
0E
1)
1*
0"
1K
0#
1J
0I
0'
#13100
0$
1#
1"
0(
1Z
#13200
1I
#13300
1$
#13600
0-
#14400
1-
b11111111 +
b1 ,
b10100 0
0<
0=
0>
0?
0@
1C
17
19
1:
b1001 /
b111100001 3
b111100001 2
#14500
1P
1S
0M
1O
1V
0X
1\
0^
1_
0a
1b
0d
#14600
0*
0"
1c
0K
0#
1`
0J
0$
1]
0H
1&
1E
0)
1'
#14700
1Q
1%
0Z
1J
1K
1*
#14800
0I
1F
#14900
0'
1T
1$
0]
#15000
0J
1G
#15100
0&
1W
1#
0`
#15200
0K
1H
0-
#15300
0%
1Z
1"
0c
#15400
0*
1I
#15500
0$
1]
#15600
1J
#15700
0#
1`
#15800
1K
#15900
0"
1c
#16000
1*
1-
b1010 /
b100000000 3
b100000000 2
#16800
0-
#17600
1-
b1011 /
1.
bx 2
