HW1-3/3-ASU/barrel_shifter_gate.v
module barrel_shifter_gate(in, shift, out);
input  [7:0] in;
input  [2:0] shift;
output [7:0] out;

/*Write your code here*/
wire [7:0] x1;
wire [7:0] x2;
reg zero = 0;

mux m1_1(x1[0],in[0],zero,shift[0]);
mux m1_2(x1[1],in[1],in[0],shift[0]);
mux m1_3(x1[2],in[2],in[1],shift[0]);
mux m1_4(x1[3],in[3],in[2],shift[0]);
mux m1_5(x1[4],in[4],in[3],shift[0]);
mux m1_6(x1[5],in[5],in[4],shift[0]);
mux m1_7(x1[6],in[6],in[5],shift[0]);
mux m1_8(x1[7],in[7],in[6],shift[0]);

mux m2_1(x2[0],x1[0],zero,shift[1]);
mux m2_2(x2[1],x1[1],zero,shift[1]);
mux m2_3(x2[2],x1[2],x1[0],shift[1]);
mux m2_4(x2[3],x1[3],x1[1],shift[1]);
mux m2_5(x2[4],x1[4],x1[2],shift[1]);
mux m2_6(x2[5],x1[5],x1[3],shift[1]);
mux m2_7(x2[6],x1[6],x1[4],shift[1]);
mux m2_8(x2[7],x1[7],x1[5],shift[1]);

mux m4_1(out[0],x2[0],zero,shift[2]);
mux m4_2(out[1],x2[1],zero,shift[2]);
mux m4_3(out[2],x2[2],zero,shift[2]);
mux m4_4(out[3],x2[3],zero,shift[2]);
mux m4_5(out[4],x2[4],x2[0],shift[2]);
mux m4_6(out[5],x2[5],x2[1],shift[2]);
mux m4_7(out[6],x2[6],x2[2],shift[2]);
mux m4_8(out[7],x2[7],x2[3],shift[2]);


/*End of code*/
endmodule

module mux (x,a,b,sel);
input 	a,b,sel;
output 	x;
wire sel_i,w1,w2;

not #1 n0(sel_i,sel);
and #1 a1(w1,a,sel_i);
and #1 a2(w2,b,sel);
or  #1 o1(x,w1,w2);

	
endmodule

HW1-3/3-ASU/adder_gate.v
module pfa(a,b,p,g);  //A one PFA. I need 16 of them5
    //wire w;
    //reg a,b,c;
    //wire sum,p,g;
    input a,b;
    output p,g;

    //xor (w,a,b);     //repeated P. May need it may not. 
    and (g,a,b);  //Gi
    xor (p,a,b);   //Pi
    //xor (sum,w,c);  //sum 
endmodule
                //input    output   
module half_adder_gate(A,B,Cin,carry,out);
    input [3:0] A,B;
    input Cin;
    output [3:0] out;
    output carry;    
    wire [3:0] P,G;
    //wire p0,g0;
    //wire b1,b2,b3;
    wire w3,w4,w5,w6,w7,w8,w9,w10,w11,w12,w13,w14,w15,w16,w17,w18;
    wire w19,w20,w21,w22,w23,w24,w25,w26,w27,w28,w29,w30,w31,w32,w33,w34,w35,w36,w37,w38;
    wire c1,c2,c3,c4,c5,c6,c7;

        pfa PFA0(A[0],B[0],P[0],G[0]);
        and (w3,P[0],Cin);
        or (c1,G[0],w3);
        pfa PFA1(A[1],B[1],P[1],G[1]);
        and (w4,P[1],G[0]);
        and (w5,P[1],P[0],Cin);
        or (c2,G[1],w4,w5); 
        pfa PFA2(A[2],B[2],P[2],G[2]);
        and (w6,P[2],G[1]);
        and (w7,P[2],P[1],G[0]);
        and (w8,P[2],P[1],P[0],Cin);
        or (c3,G[2],w6,w7,w8);
        pfa PFA3(A[3],B[3],P[3],G[3]);
        and (w9,P[3],G[2]);
        and (w10,P[3],P[2],G[1]);
        and (w11,P[3],P[2],P[1],G[0]);
        and (w12,P[3],P[2],P[1],P[0],Cin);
        or(carry,w9,w10,w11,w12);
        
  

        xor (out[0],P[0],Cin);
        xor (out[1],P[1],c1);
        xor (out[2],P[2],c2);
        xor (out[3],P[3],c3);
     




        //propagate
        //and (p0,P[3],P[2],P[1],P[0]);

        //GENERATE
        //and (w,P[3],G[2]);
        //and (w1,P[3],P[2],G[1]);
        //and (w2,P[3],P[2],P[1],G[0]);
        //or (w,w1,w2);
//CLA 


       
     
        
       
endmodule   

module adder_gate(x,y,carry,out);
input [7:0] x, y;
output carry;
output [7:0] out;
wire c4;
reg Cin=0;
half_adder_gate h1(x[3:0],y[3:0],Cin,c4,out[3:0]);
half_adder_gate h2(x[7:4],y[7:4],c4,carry,out[7:4]);

endmodule

HW1-3/3-ASU/asu_gate.v
module asu_gate (x, y, mode, carry, out);
input [7:0] x, y;
input mode;
output carry;
output [7:0] out;

/*Write your code here*/
wire [7:0] output_a;
wire [7:0] output_b;
adder_gate a(x,y,carry_a,output_a);
barrel_shifter_gate b(x,y[2:0],output_b);

mux1 #2.5 mux_3_1(out[0],output_b[0],output_a[0],mode);
mux1 #2.5 mux_3_2(out[1],output_b[1],output_a[1],mode);
mux1 #2.5 mux_3_3(out[2],output_b[2],output_a[2],mode);
mux1 #2.5 mux_3_4(out[3],output_b[3],output_a[3],mode);
mux1 #2.5 mux_3_5(out[4],output_b[4],output_a[4],mode);
mux1 #2.5 mux_3_6(out[5],output_b[5],output_a[5],mode);
mux1 #2.5 mux_3_7(out[6],output_b[6],output_a[6],mode);
mux1 #2.5 mux_3_8(out[7],output_b[7],output_a[7],mode);
mux1 #2.5 mux_3_c(carry,0,carry_a,mode);


/*End of code*/


endmodule


module mux1 (x,a,b,sel);
input 	a,b,sel;
output 	x;
wire sel_i,w1,w2;

not n0(sel_i,sel);
and a1(w1,a,sel_i);
and a2(w2,b,sel);
or  o1(x,w1,w2);

	
endmodule

HW1-3/3-ASU/asu_gate_test.v
`timescale 1ns/10ps
`define CYCLE 9.6
`define SELFILE "Msel.pattern"
`define INFILE "Min.pattern"
`define OUTFILE "Mout_golden.pattern" 

module asu_gate_test;
parameter pattern_num = 10;
wire [7:0] out;
wire carry;
reg [7:0] x, y;
reg mode;
reg  clk;
reg  stop;
integer i, num, error;

reg [8:0] ans_out;
reg [8:0] mux_out;

reg [1:0] data_base0 [0:100];
reg [7:0] data_base1 [0:100];
reg [8:0] data_base2 [0:100];

asu_gate t (x, y, mode, carry, out);

initial begin
	$readmemh(`SELFILE  , data_base0);
	$readmemh(`INFILE  , data_base1);
	$readmemh(`OUTFILE , data_base2);
	clk = 1'b1;
	error = 0;
	stop = 0;
	i=0;
end

always begin #(`CYCLE * 0.5) clk = ~clk;
end

initial begin
	mode = data_base0[0];
	x[7:0] = data_base1[0];
	y[7:0] = data_base1[1];
	
	for(num = 2; num < (pattern_num * 2); num = num + 2) begin
		@(posedge clk) begin
			mode = data_base0[num / 2];
			x[7:0] = data_base1[num];
			y[7:0] = data_base1[num + 1];
		end
	end
end


always@(posedge clk) begin
	i <= i + 1;
	if (i >= pattern_num)
		stop <= 1;
end

always@(posedge clk ) begin
	mux_out <= {carry, out};
	ans_out <= data_base2[i];
	if(mux_out !== ans_out) begin
		error <= error + 1;
		$display("An ERROR occurs at no.%d pattern: Output %b != answer %b.\n", i, mux_out, ans_out);
	end
end

initial begin
	@(posedge stop) begin
		if(error == 0) begin
			$display("==========================================\n");
			$display("======  Congratulation! You Pass!  =======\n");
			$display("==========================================\n");
		end
		else begin
			$display("===============================\n");
			$display("There are %d errors.", error);
			$display("===============================\n");
		end
		$finish;
	end
end

/*================Dumping Waveform files====================*/
initial begin
$dumpfile("mux.vcd");
$dumpvars;
/* 	$fsdbDumpfile("mux.fsdb");
	$fsdbDumpvars;  */
end

endmodule

HW1-3/3-ASU/mux.vcd
$date
    Mar 29, 2018  17:22:42
$end
$version
    TOOL:	ncsim	10.20-s114
$end
$timescale
    10 ps
$end

$scope module asu_gate_test $end
$var parameter 32 !    pattern_num  $end
$var wire      8 "    out [7:0] $end
$var wire      1 #    carry  $end
$var reg       8 $    x [7:0] $end
$var reg       8 %    y [7:0] $end
$var reg       1 &    mode  $end
$var reg       1 '    clk  $end
$var reg       1 (    stop  $end
$var integer  32 )    i  $end
$var integer  32 *    num  $end
$var integer  32 +    error  $end
$var reg       9 ,    ans_out [8:0] $end
$var reg       9 -    mux_out [8:0] $end

$scope module t $end
$var wire      1 .    x [7] $end
$var wire      1 /    x [6] $end
$var wire      1 0    x [5] $end
$var wire      1 1    x [4] $end
$var wire      1 2    x [3] $end
$var wire      1 3    x [2] $end
$var wire      1 4    x [1] $end
$var wire      1 5    x [0] $end
$var wire      1 6    y [7] $end
$var wire      1 7    y [6] $end
$var wire      1 8    y [5] $end
$var wire      1 9    y [4] $end
$var wire      1 :    y [3] $end
$var wire      1 ;    y [2] $end
$var wire      1 <    y [1] $end
$var wire      1 =    y [0] $end
$var wire      1 >    mode  $end
$var wire      1 #    carry  $end
$var wire      8 "    out [7:0] $end
$var wire      1 ?    output_a [7] $end
$var wire      1 @    output_a [6] $end
$var wire      1 A    output_a [5] $end
$var wire      1 B    output_a [4] $end
$var wire      1 C    output_a [3] $end
$var wire      1 D    output_a [2] $end
$var wire      1 E    output_a [1] $end
$var wire      1 F    output_a [0] $end
$var wire      1 G    output_b [7] $end
$var wire      1 H    output_b [6] $end
$var wire      1 I    output_b [5] $end
$var wire      1 J    output_b [4] $end
$var wire      1 K    output_b [3] $end
$var wire      1 L    output_b [2] $end
$var wire      1 M    output_b [1] $end
$var wire      1 N    output_b [0] $end

$scope module a $end
$var wire      1 .    x [7] $end
$var wire      1 /    x [6] $end
$var wire      1 0    x [5] $end
$var wire      1 1    x [4] $end
$var wire      1 2    x [3] $end
$var wire      1 3    x [2] $end
$var wire      1 4    x [1] $end
$var wire      1 5    x [0] $end
$var wire      1 6    y [7] $end
$var wire      1 7    y [6] $end
$var wire      1 8    y [5] $end
$var wire      1 9    y [4] $end
$var wire      1 :    y [3] $end
$var wire      1 ;    y [2] $end
$var wire      1 <    y [1] $end
$var wire      1 =    y [0] $end
$var wire      1 #    carry  $end
$var wire      1 ?    out [7] $end
$var wire      1 @    out [6] $end
$var wire      1 A    out [5] $end
$var wire      1 B    out [4] $end
$var wire      1 C    out [3] $end
$var wire      1 D    out [2] $end
$var wire      1 E    out [1] $end
$var wire      1 F    out [0] $end
$var wire      1 O    c4  $end
$var reg       1 P    Cin  $end

$scope module h1 $end
$var wire      1 2    A [3] $end
$var wire      1 3    A [2] $end
$var wire      1 4    A [1] $end
$var wire      1 5    A [0] $end
$var wire      1 :    B [3] $end
$var wire      1 ;    B [2] $end
$var wire      1 <    B [1] $end
$var wire      1 =    B [0] $end
$var wire      1 Q    Cin  $end
$var wire      1 C    out [3] $end
$var wire      1 D    out [2] $end
$var wire      1 E    out [1] $end
$var wire      1 F    out [0] $end
$var wire      1 O    carry  $end
$var wire      1 R    P [3] $end
$var wire      1 S    P [2] $end
$var wire      1 T    P [1] $end
$var wire      1 U    P [0] $end
$var wire      1 V    G [3] $end
$var wire      1 W    G [2] $end
$var wire      1 X    G [1] $end
$var wire      1 Y    G [0] $end
$var wire      1 Z    w3  $end
$var wire      1 [    w4  $end
$var wire      1 \    w5  $end
$var wire      1 ]    w6  $end
$var wire      1 ^    w7  $end
$var wire      1 _    w8  $end
$var wire      1 `    w9  $end
$var wire      1 a    w10  $end
$var wire      1 b    w11  $end
$var wire      1 c    w12  $end
$var wire      1 d    c1  $end
$var wire      1 e    c2  $end
$var wire      1 f    c3  $end
$var wire      1 g    c4  $end
$var wire      1 g    c5  $end
$var wire      1 g    c6  $end
$var wire      1 g    c7  $end

$scope module PFA0 $end
$var wire      1 5    a  $end
$var wire      1 =    b  $end
$var wire      1 U    p  $end
$var wire      1 Y    g  $end
$upscope $end


$scope module PFA1 $end
$var wire      1 4    a  $end
$var wire      1 <    b  $end
$var wire      1 T    p  $end
$var wire      1 X    g  $end
$upscope $end


$scope module PFA2 $end
$var wire      1 3    a  $end
$var wire      1 ;    b  $end
$var wire      1 S    p  $end
$var wire      1 W    g  $end
$upscope $end


$scope module PFA3 $end
$var wire      1 2    a  $end
$var wire      1 :    b  $end
$var wire      1 R    p  $end
$var wire      1 V    g  $end
$upscope $end

$upscope $end


$scope module h2 $end
$var wire      1 .    A [3] $end
$var wire      1 /    A [2] $end
$var wire      1 0    A [1] $end
$var wire      1 1    A [0] $end
$var wire      1 6    B [3] $end
$var wire      1 7    B [2] $end
$var wire      1 8    B [1] $end
$var wire      1 9    B [0] $end
$var wire      1 O    Cin  $end
$var wire      1 ?    out [3] $end
$var wire      1 @    out [2] $end
$var wire      1 A    out [1] $end
$var wire      1 B    out [0] $end
$var wire      1 #    carry  $end
$var wire      1 h    P [3] $end
$var wire      1 i    P [2] $end
$var wire      1 j    P [1] $end
$var wire      1 k    P [0] $end
$var wire      1 l    G [3] $end
$var wire      1 m    G [2] $end
$var wire      1 n    G [1] $end
$var wire      1 o    G [0] $end
$var wire      1 p    w3  $end
$var wire      1 q    w4  $end
$var wire      1 r    w5  $end
$var wire      1 s    w6  $end
$var wire      1 t    w7  $end
$var wire      1 u    w8  $end
$var wire      1 v    w9  $end
$var wire      1 w    w10  $end
$var wire      1 x    w11  $end
$var wire      1 y    w12  $end
$var wire      1 z    c1  $end
$var wire      1 {    c2  $end
$var wire      1 |    c3  $end
$var wire      1 g    c4  $end
$var wire      1 g    c5  $end
$var wire      1 g    c6  $end
$var wire      1 g    c7  $end

$scope module PFA0 $end
$var wire      1 1    a  $end
$var wire      1 9    b  $end
$var wire      1 k    p  $end
$var wire      1 o    g  $end
$upscope $end


$scope module PFA1 $end
$var wire      1 0    a  $end
$var wire      1 8    b  $end
$var wire      1 j    p  $end
$var wire      1 n    g  $end
$upscope $end


$scope module PFA2 $end
$var wire      1 /    a  $end
$var wire      1 7    b  $end
$var wire      1 i    p  $end
$var wire      1 m    g  $end
$upscope $end


$scope module PFA3 $end
$var wire      1 .    a  $end
$var wire      1 6    b  $end
$var wire      1 h    p  $end
$var wire      1 l    g  $end
$upscope $end

$upscope $end

$upscope $end


$scope module b $end
$var wire      1 .    in [7] $end
$var wire      1 /    in [6] $end
$var wire      1 0    in [5] $end
$var wire      1 1    in [4] $end
$var wire      1 2    in [3] $end
$var wire      1 3    in [2] $end
$var wire      1 4    in [1] $end
$var wire      1 5    in [0] $end
$var wire      1 ;    shift [2] $end
$var wire      1 <    shift [1] $end
$var wire      1 =    shift [0] $end
$var wire      1 G    out [7] $end
$var wire      1 H    out [6] $end
$var wire      1 I    out [5] $end
$var wire      1 J    out [4] $end
$var wire      1 K    out [3] $end
$var wire      1 L    out [2] $end
$var wire      1 M    out [1] $end
$var wire      1 N    out [0] $end
$var wire      1 }    x1 [7] $end
$var wire      1 ~    x1 [6] $end
$var wire      1 !!   x1 [5] $end
$var wire      1 "!   x1 [4] $end
$var wire      1 #!   x1 [3] $end
$var wire      1 $!   x1 [2] $end
$var wire      1 %!   x1 [1] $end
$var wire      1 &!   x1 [0] $end
$var wire      1 '!   x2 [7] $end
$var wire      1 (!   x2 [6] $end
$var wire      1 )!   x2 [5] $end
$var wire      1 *!   x2 [4] $end
$var wire      1 +!   x2 [3] $end
$var wire      1 ,!   x2 [2] $end
$var wire      1 -!   x2 [1] $end
$var wire      1 .!   x2 [0] $end
$var reg       1 /!   zero  $end

$scope module m1_1 $end
$var wire      1 5    a  $end
$var wire      1 0!   b  $end
$var wire      1 =    sel  $end
$var wire      1 &!   x  $end
$var wire      1 1!   sel_i  $end
$var wire      1 2!   w1  $end
$var wire      1 3!   w2  $end
$upscope $end


$scope module m1_2 $end
$var wire      1 4    a  $end
$var wire      1 5    b  $end
$var wire      1 =    sel  $end
$var wire      1 %!   x  $end
$var wire      1 1!   sel_i  $end
$var wire      1 4!   w1  $end
$var wire      1 5!   w2  $end
$upscope $end


$scope module m1_3 $end
$var wire      1 3    a  $end
$var wire      1 4    b  $end
$var wire      1 =    sel  $end
$var wire      1 $!   x  $end
$var wire      1 1!   sel_i  $end
$var wire      1 6!   w1  $end
$var wire      1 7!   w2  $end
$upscope $end


$scope module m1_4 $end
$var wire      1 2    a  $end
$var wire      1 3    b  $end
$var wire      1 =    sel  $end
$var wire      1 #!   x  $end
$var wire      1 1!   sel_i  $end
$var wire      1 8!   w1  $end
$var wire      1 9!   w2  $end
$upscope $end


$scope module m1_5 $end
$var wire      1 1    a  $end
$var wire      1 2    b  $end
$var wire      1 =    sel  $end
$var wire      1 "!   x  $end
$var wire      1 1!   sel_i  $end
$var wire      1 :!   w1  $end
$var wire      1 ;!   w2  $end
$upscope $end


$scope module m1_6 $end
$var wire      1 0    a  $end
$var wire      1 1    b  $end
$var wire      1 =    sel  $end
$var wire      1 !!   x  $end
$var wire      1 1!   sel_i  $end
$var wire      1 <!   w1  $end
$var wire      1 =!   w2  $end
$upscope $end


$scope module m1_7 $end
$var wire      1 /    a  $end
$var wire      1 0    b  $end
$var wire      1 =    sel  $end
$var wire      1 ~    x  $end
$var wire      1 1!   sel_i  $end
$var wire      1 >!   w1  $end
$var wire      1 ?!   w2  $end
$upscope $end


$scope module m1_8 $end
$var wire      1 .    a  $end
$var wire      1 /    b  $end
$var wire      1 =    sel  $end
$var wire      1 }    x  $end
$var wire      1 1!   sel_i  $end
$var wire      1 @!   w1  $end
$var wire      1 A!   w2  $end
$upscope $end


$scope module m2_1 $end
$var wire      1 &!   a  $end
$var wire      1 0!   b  $end
$var wire      1 <    sel  $end
$var wire      1 .!   x  $end
$var wire      1 B!   sel_i  $end
$var wire      1 C!   w1  $end
$var wire      1 D!   w2  $end
$upscope $end


$scope module m2_2 $end
$var wire      1 %!   a  $end
$var wire      1 0!   b  $end
$var wire      1 <    sel  $end
$var wire      1 -!   x  $end
$var wire      1 B!   sel_i  $end
$var wire      1 E!   w1  $end
$var wire      1 D!   w2  $end
$upscope $end


$scope module m2_3 $end
$var wire      1 $!   a  $end
$var wire      1 &!   b  $end
$var wire      1 <    sel  $end
$var wire      1 ,!   x  $end
$var wire      1 B!   sel_i  $end
$var wire      1 F!   w1  $end
$var wire      1 G!   w2  $end
$upscope $end


$scope module m2_4 $end
$var wire      1 #!   a  $end
$var wire      1 %!   b  $end
$var wire      1 <    sel  $end
$var wire      1 +!   x  $end
$var wire      1 B!   sel_i  $end
$var wire      1 H!   w1  $end
$var wire      1 I!   w2  $end
$upscope $end


$scope module m2_5 $end
$var wire      1 "!   a  $end
$var wire      1 $!   b  $end
$var wire      1 <    sel  $end
$var wire      1 *!   x  $end
$var wire      1 B!   sel_i  $end
$var wire      1 J!   w1  $end
$var wire      1 K!   w2  $end
$upscope $end


$scope module m2_6 $end
$var wire      1 !!   a  $end
$var wire      1 #!   b  $end
$var wire      1 <    sel  $end
$var wire      1 )!   x  $end
$var wire      1 B!   sel_i  $end
$var wire      1 L!   w1  $end
$var wire      1 M!   w2  $end
$upscope $end


$scope module m2_7 $end
$var wire      1 ~    a  $end
$var wire      1 "!   b  $end
$var wire      1 <    sel  $end
$var wire      1 (!   x  $end
$var wire      1 B!   sel_i  $end
$var wire      1 N!   w1  $end
$var wire      1 O!   w2  $end
$upscope $end


$scope module m2_8 $end
$var wire      1 }    a  $end
$var wire      1 !!   b  $end
$var wire      1 <    sel  $end
$var wire      1 '!   x  $end
$var wire      1 B!   sel_i  $end
$var wire      1 P!   w1  $end
$var wire      1 Q!   w2  $end
$upscope $end


$scope module m4_1 $end
$var wire      1 .!   a  $end
$var wire      1 0!   b  $end
$var wire      1 ;    sel  $end
$var wire      1 N    x  $end
$var wire      1 R!   sel_i  $end
$var wire      1 S!   w1  $end
$var wire      1 T!   w2  $end
$upscope $end


$scope module m4_2 $end
$var wire      1 -!   a  $end
$var wire      1 0!   b  $end
$var wire      1 ;    sel  $end
$var wire      1 M    x  $end
$var wire      1 R!   sel_i  $end
$var wire      1 U!   w1  $end
$var wire      1 T!   w2  $end
$upscope $end


$scope module m4_3 $end
$var wire      1 ,!   a  $end
$var wire      1 0!   b  $end
$var wire      1 ;    sel  $end
$var wire      1 L    x  $end
$var wire      1 R!   sel_i  $end
$var wire      1 V!   w1  $end
$var wire      1 T!   w2  $end
$upscope $end


$scope module m4_4 $end
$var wire      1 +!   a  $end
$var wire      1 0!   b  $end
$var wire      1 ;    sel  $end
$var wire      1 K    x  $end
$var wire      1 R!   sel_i  $end
$var wire      1 W!   w1  $end
$var wire      1 T!   w2  $end
$upscope $end


$scope module m4_5 $end
$var wire      1 *!   a  $end
$var wire      1 .!   b  $end
$var wire      1 ;    sel  $end
$var wire      1 J    x  $end
$var wire      1 R!   sel_i  $end
$var wire      1 X!   w1  $end
$var wire      1 Y!   w2  $end
$upscope $end


$scope module m4_6 $end
$var wire      1 )!   a  $end
$var wire      1 -!   b  $end
$var wire      1 ;    sel  $end
$var wire      1 I    x  $end
$var wire      1 R!   sel_i  $end
$var wire      1 Z!   w1  $end
$var wire      1 [!   w2  $end
$upscope $end


$scope module m4_7 $end
$var wire      1 (!   a  $end
$var wire      1 ,!   b  $end
$var wire      1 ;    sel  $end
$var wire      1 H    x  $end
$var wire      1 R!   sel_i  $end
$var wire      1 \!   w1  $end
$var wire      1 ]!   w2  $end
$upscope $end


$scope module m4_8 $end
$var wire      1 '!   a  $end
$var wire      1 +!   b  $end
$var wire      1 ;    sel  $end
$var wire      1 G    x  $end
$var wire      1 R!   sel_i  $end
$var wire      1 ^!   w1  $end
$var wire      1 _!   w2  $end
$upscope $end

$upscope $end

$upscope $end

$upscope $end

$enddefinitions $end
$dumpvars
b1010 !
bx "
x#
b10101010 $
b0 %
0&
1'
0(
b0 )
b10 *
b0 +
bx ,
bx -
1.
0/
10
01
12
03
14
05
06
07
08
09
0:
0;
0<
0=
0>
x?
x@
xA
xB
xC
xD
xE
xF
xG
xH
xI
xJ
xK
xL
xM
xN
xO
0P
0Q
xR
xS
xT
xU
xV
xW
xX
xY
xZ
x[
x\
x]
x^
x_
x`
xa
xb
xc
xd
xe
xf
zg
xh
xi
xj
xk
xl
xm
xn
xo
xp
xq
xr
xs
xt
xu
xv
xw
xx
xy
xz
x{
x|
x}
x~
x!!
x"!
x#!
x$!
x%!
x&!
x'!
x(!
x)!
x*!
x+!
x,!
x-!
x.!
0/!
00!
x1!
x2!
x3!
x4!
x5!
x6!
x7!
x8!
x9!
x:!
x;!
x<!
x=!
x>!
x?!
x@!
xA!
xB!
xC!
xD!
xE!
xF!
xG!
xH!
xI!
xJ!
xK!
xL!
xM!
xN!
xO!
xP!
xQ!
xR!
xS!
xT!
xU!
xV!
xW!
xX!
xY!
xZ!
x[!
x\!
x]!
x^!
x_!
$end
#100
0Z
0\
0_
0c
0U
02!
1T
0S
06!
1R
0k
0:!
1j
0i
0>!
1h
11!
0A!
0?!
0=!
0;!
09!
07!
05!
03!
0Y
1B!
0Q!
0O!
0M!
0K!
0I!
0G!
0D!
0X
1R!
0_!
0]!
0[!
0Y!
0T!
0W
0V
0o
0n
0m
0l
#200
0v
0q
0`
0d
0[
0&!
0$!
0"!
0~
1@!
1<!
18!
14!
0t
0s
0x
0w
0p
0r
0u
0y
0^
0]
0b
0a
0F
#300
0O
0f
0#
0|
0{
0z
1%!
1#!
1!!
1}
0N!
0J!
0F!
0C!
0e
1E
#400
0D
0.!
0,!
0*!
0(!
1P!
1L!
1H!
1E!
1A
0@
1?
1C
0B
#475
0'
#500
1-!
1+!
1)!
1'!
0\!
0X!
0V!
0S!
#600
0N
0L
0J
0H
1^!
1Z!
1W!
1U!
#700
1M
1K
1I
1G
#950
b10101010 "
1'
b1 %
b100 *
1=
b1 )
b10101010 -
b10101010 ,
#1050
01!
1U
1?!
1;!
17!
#1150
1$!
1"!
1~
1F
0@!
0<!
08!
04!
#1250
0%!
0#!
0!!
0}
1N!
1J!
1F!
#1350
1,!
1*!
1(!
0P!
0L!
0H!
0E!
#1425
0'
#1450
0-!
0+!
0)!
0'!
1\!
1X!
1V!
#1550
1L
1J
1H
0^!
0Z!
0W!
0U!
#1650
0M
0K
0I
0G
#1900
b1010100 "
1'
b10 %
b110 *
1<
0=
b10 )
b1010100 -
b1010100 ,
#2000
11!
0U
0?!
0;!
07!
0B!
0T
1O!
1K!
1X
#2100
1e
0E
0N!
0J!
0F!
0$!
0"!
0~
0F
1@!
1<!
18!
14!
#2200
1%!
1#!
1!!
1}
0O!
0K!
0,!
1D
#2300
0V!
0*!
0(!
1Q!
1M!
1I!
#2375
0'
#2400
1+!
1)!
1'!
0\!
0X!
0L
#2500
0J
0H
1^!
1Z!
1W!
#2600
1K
1I
1G
#2850
b10101000 "
1'
b11 %
b1000 *
1=
b11 )
b10101000 -
b10101000 ,
#2950
01!
1U
1?!
1;!
17!
#3050
1$!
1"!
1~
1F
0@!
0<!
08!
04!
#3150
0%!
0#!
0!!
0}
1O!
1K!
#3250
1*!
1(!
0Q!
0M!
0I!
#3325
0'
#3350
0+!
0)!
0'!
1\!
1X!
#3450
1J
1H
0^!
0Z!
0W!
#3550
0K
0I
0G
#3800
b1010000 "
1'
1&
b1110000 $
b1111 %
b1010 *
1:
1;
0.
1/
11
02
04
1>
b100 )
b1010000 -
b1010000 ,
#3900
1T
07!
0X
0;!
1k
1=!
1i
1A!
0h
0R!
1S
#4000
0D
0\!
0X!
0?
1}
1@
1!!
1B
0"!
0e
0$!
1E
#4100
0K!
1D
0O!
1Q!
0J
0H
#4200
1'!
0(!
0*!
#4275
0'
#4350
b1111111 "
#4750
1'
b11111111 $
b1 %
b1100 *
0:
0;
0<
1.
12
13
14
15
b101 )
b1111111 -
b1111111 ,
#4850
0U
15!
1Y
17!
19!
1;!
1h
1B!
0Q!
1R!
#4950
1^!
0'!
1P!
1N!
1L!
1?
1"!
1#!
1$!
1d
1[
1^
1b
1%!
0F
#5050
1E!
1O
1f
1e
0E
1F!
1H!
1J!
1)!
1(!
1'!
1G
#5150
1\!
1Z!
1*!
1+!
1,!
0D
0C
0B
1p
1r
1u
1y
1-!
#5225
0'
#5250
1U!
1#
1|
1{
1z
1V!
1W!
1X!
1I
1H
#5350
1J
1K
1L
0A
0@
0?
1M
#5600
b0 "
#5700
1'
b1011011 $
b1101010 %
b1110 *
17
18
1:
1<
0=
0.
00
03
b110 )
b100000000 -
b100000000 ,
#5800
0S
0h
11!
1U
0A!
0?!
0=!
0;!
09!
07!
05!
0Y
0B!
0T
1Q!
1O!
1M!
1K!
1I!
1X
0R
1V
0i
1m
#5900
1@
0u
1C
1E
0P!
0N!
0L!
0J!
0H!
0F!
0E!
0d
0[
0%!
0$!
0#!
0"!
0!!
0~
0}
1F
1>!
1:!
18!
14!
12!
1?
0y
1D
0^
0b
#6000
0f
0#
1&!
1%!
1#!
1"!
1~
0Q!
0K!
0E
0-!
0,!
#6100
0V!
0U!
0*!
0'!
1G!
0C
#6175
0'
#6200
1,!
0^!
0X!
0M
0L
#6300
0J
0G
1V!
#6350
b11000101 "
#6400
1L
#6650
1'
b11101 $
b11010001 %
b10000 *
16
08
19
0:
0<
1=
0/
13
04
b111 )
b11000101 -
b11000101 ,
#6750
04!
1S
19!
16!
1i
0>!
0m
01!
0U
1=!
1;!
15!
1Y
1B!
0O!
0M!
0I!
0G!
0X
1R
0V
0k
1o
0j
1h
#6850
0?
1A
1B
0p
0r
0O
1C
0e
0,!
0+!
0)!
0(!
1N!
1J!
1H!
1E!
1C!
1d
1!!
0F
0:!
08!
06!
02!
0|
0~
0@
#6950
0N!
1?
0&!
1L!
1E
1.!
1-!
1+!
1*!
0\!
0Z!
0V!
0B
0{
#7050
1@
0L
0I
0H
1X!
1U!
1S!
1)!
0C!
#7125
0'
#7150
0.!
1Z!
1N
1M
1J
#7250
1I
0S!
#7300
b11101110 "
#7350
0N
#7600
1'
b11101001 $
b11111000 %
b10010 *
18
1:
0=
1.
1/
10
01
03
b1000 )
b11101110 -
b11101110 ,
#7700
0S
1k
0o
1n
0i
1m
0h
1l
11!
1U
0=!
0;!
09!
05!
0Y
0R
1V
#7800
1O
0C
0d
0%!
0#!
0"!
0!!
1F
1@!
1>!
1<!
18!
12!
1#
0?
1|
0@
1{
0z
0D
#7900
0A
1@
1?
1&!
1#!
1!!
1~
1}
0J!
0E!
0E
1p
#8000
1z
0-!
0*!
1P!
1N!
1C!
#8075
0'
#8100
1.!
1(!
1'!
0X!
0U!
1A
#8200
0M
0J
1^!
1\!
1S!
#8300
1N
1H
1G
#8350
b11100001 "
#8550
1'
b11110000 $
b11011 %
b10100 *
06
07
08
1<
1=
11
02
05
b1001 )
b111100001 -
b111100001 ,
#8650
02!
1R
08!
0V
0k
1=!
1:!
1o
01!
1A!
1?!
0B!
1T
1Q!
1M!
1G!
1j
0n
1i
0m
1h
0l
#8750
0#
0?
1x
0|
0@
1t
0{
0A
1q
1,!
1E
0P!
0N!
0L!
0H!
0C!
0@!
0>!
0<!
0:!
1B
0p
0O
0#!
1C
0&!
#8850
0G!
0M!
0B
0.!
0+!
0(!
1V!
1{
1|
1#
#8950
1L
0\!
0W!
0S!
0)!
0,!
#9025
0'
#9050
0V!
0Z!
0N
0K
0H
#9100
b1011 "
#9150
0I
0L
#9500
1'
b1010 )
b100001011 -
b100001011 ,
#9975
0'
#10450
1'
b1011 )
1(
bx ,
