HW1-3/2-barrel_shifter/barrel_shifter_gate.v
module barrel_shifter_gate(in, shift, out);
input  [7:0] in;
input  [2:0] shift;
output [7:0] out;

/*Write your code here*/
reg [7:0] x1;
reg [7:0] x2;
mux m1_1(x1[0],in[0],zero,shift[0]);
mux m1_2(x1[1],in[1],in[0],shift[0]);
mux m1_3(x1[2],in[2],in[1],shift[0]);
mux m1_4(x1[3],in[3],in[2],shift[0]);
mux m1_5(x1[4],in[4],in[3],shift[0]);
mux m1_6(x1[5],in[5],in[4],shift[0]);
mux m1_7(x1[6],in[6],in[5],shift[0]);
mux m1_8(x1[7],in[7],in[6],shift[0]);

mux m2_1(x2[0],x1[0],zero,shift[1]);
mux m2_2(x2[1],x1[1],zero,shift[1]);
mux m2_3(x2[2],x1[2],x1[0],shift[1]);
mux m2_4(x2[3],x1[3],x1[1],shift[1]);
mux m2_5(x2[4],x1[4],x1[2],shift[1]);
mux m2_6(x2[5],x1[5],x1[3],shift[1]);
mux m2_7(x2[6],x1[6],x1[4],shift[1]);
mux m2_8(x2[7],x1[7],x1[5],shift[1]);

mux m4_1(out[0],x2[0],zero,shift[2]);
mux m4_2(out[1],x2[1],zero,shift[2]);
mux m4_3(out[2],x2[2],zero,shift[2]);
mux m4_4(out[3],x2[3],zero,shift[2]);
mux m4_5(out[4],x2[4],x2[0],shift[2]);
mux m4_6(out[5],x2[5],x2[1],shift[2]);
mux m4_7(out[6],x2[6],x2[2],shift[2]);
mux m4_8(out[7],x2[7],x2[3],shift[2]);


/*End of code*/
endmodule

module mux (x,a,b,sel);
input 	a,b,sel;
output 	x;
wire sel_i,w1,w2;

not n0(sel_i,sel);
and a1(w1,a,sel_i);
and a2(w2,b,sel);
or  o1(x,w1,w2);

	
endmodule

HW1-3/2-barrel_shifter/barrel_gate_test.v
`timescale 1ns/10ps
`define CYCLE 5
`define INFILE "Bin.pattern"
`define OUTFILE "Bout_golden.pattern" 

module barrel_gate_test;
parameter pattern_num = 8;
wire [7:0] out;
wire carry;
reg [7:0] x, y;
reg  clk;
reg  stop;
integer i, num, error;

reg [7:0] ans_out;
reg [7:0] barrel_out;

reg [7:0] data_base1 [0:100];
reg [7:0] data_base2 [0:100];

barrel_shifter_gate B (x, y[2:0], out);

initial begin
	$readmemh(`INFILE  , data_base1);
	$readmemh(`OUTFILE , data_base2);
	clk = 1'b1;
	error = 0;
	stop = 0;
	i=0;
end

always begin #(`CYCLE * 0.5) clk = ~clk;
end

initial begin
	x[7:0] = data_base1[0];
	y[7:0] = data_base1[1];
	
	for(num = 2; num < (pattern_num * 2); num = num + 2) begin
		@(posedge clk) begin
			x[7:0] = data_base1[num];
			y[7:0] = data_base1[num + 1];
		end
	end
end


always@(posedge clk) begin
	i <= i + 1;
	if (i >= pattern_num)
		stop <= 1;
end

always@(posedge clk ) begin
	barrel_out <= out;
	ans_out <= data_base2[i];
	if(barrel_out !== ans_out) begin
		error <= error + 1;
		$display("An ERROR occurs at no.%d pattern: Output %b != answer %b.\n", i, barrel_out, ans_out);
	end
end

initial begin
	@(posedge stop) begin
		if(error == 0) begin
			$display("==========================================\n");
			$display("======  Congratulation! You Pass!  =======\n");
			$display("==========================================\n");
		end
		else begin
			$display("===============================\n");
			$display("There are %d errors.", error);
			$display("===============================\n");
		end
		$finish;
	end
end

/*================Dumping Waveform files====================*/
initial begin
$dumpfile("barrel.vcd");
$dumpvars;
/* 	$fsdbDumpfile("barrel.fsdb");
	$fsdbDumpvars;  */
end

endmodule

HW1-3/2-barrel_shifter/barrel.vcd
$date
    Mar 29, 2018  11:44:34
$end
$version
    TOOL:	ncsim	10.20-s114
$end
$timescale
    10 ps
$end

$scope module barrel_gate_test $end
$var parameter 32 !    pattern_num  $end
$var wire      1 "    out [7] $end
$var wire      1 #    out [6] $end
$var wire      1 $    out [5] $end
$var wire      1 %    out [4] $end
$var wire      1 &    out [3] $end
$var wire      1 '    out [2] $end
$var wire      1 (    out [1] $end
$var wire      1 )    out [0] $end
$var wire      1 *    carry  $end
$var reg       8 +    x [7:0] $end
$var reg       8 ,    y [7:0] $end
$var reg       1 -    clk  $end
$var reg       1 .    stop  $end
$var integer  32 /    i  $end
$var integer  32 0    num  $end
$var integer  32 1    error  $end
$var reg       8 2    ans_out [7:0] $end
$var reg       8 3    barrel_out [7:0] $end

$scope module B $end
$var wire      1 4    in [7] $end
$var wire      1 5    in [6] $end
$var wire      1 6    in [5] $end
$var wire      1 7    in [4] $end
$var wire      1 8    in [3] $end
$var wire      1 9    in [2] $end
$var wire      1 :    in [1] $end
$var wire      1 ;    in [0] $end
$var wire      1 <    shift [2] $end
$var wire      1 =    shift [1] $end
$var wire      1 >    shift [0] $end
$var wire      1 "    out [7] $end
$var wire      1 #    out [6] $end
$var wire      1 $    out [5] $end
$var wire      1 %    out [4] $end
$var wire      1 &    out [3] $end
$var wire      1 '    out [2] $end
$var wire      1 (    out [1] $end
$var wire      1 )    out [0] $end
$var wire      1 ?    x1 [7] $end
$var wire      1 @    x1 [6] $end
$var wire      1 A    x1 [5] $end
$var wire      1 B    x1 [4] $end
$var wire      1 C    x1 [3] $end
$var wire      1 D    x1 [2] $end
$var wire      1 E    x1 [1] $end
$var wire      1 F    x1 [0] $end
$var wire      1 G    x2 [7] $end
$var wire      1 H    x2 [6] $end
$var wire      1 I    x2 [5] $end
$var wire      1 J    x2 [4] $end
$var wire      1 K    x2 [3] $end
$var wire      1 L    x2 [2] $end
$var wire      1 M    x2 [1] $end
$var wire      1 N    x2 [0] $end
$var reg       1 O    zero  $end

$scope module m1_1 $end
$var wire      1 ;    a  $end
$var wire      1 P    b  $end
$var wire      1 >    sel  $end
$var wire      1 F    x  $end
$var wire      1 Q    sel_i  $end
$var wire      1 R    w1  $end
$var wire      1 S    w2  $end
$upscope $end


$scope module m1_2 $end
$var wire      1 :    a  $end
$var wire      1 ;    b  $end
$var wire      1 >    sel  $end
$var wire      1 E    x  $end
$var wire      1 Q    sel_i  $end
$var wire      1 T    w1  $end
$var wire      1 U    w2  $end
$upscope $end


$scope module m1_3 $end
$var wire      1 9    a  $end
$var wire      1 :    b  $end
$var wire      1 >    sel  $end
$var wire      1 D    x  $end
$var wire      1 Q    sel_i  $end
$var wire      1 V    w1  $end
$var wire      1 W    w2  $end
$upscope $end


$scope module m1_4 $end
$var wire      1 8    a  $end
$var wire      1 9    b  $end
$var wire      1 >    sel  $end
$var wire      1 C    x  $end
$var wire      1 Q    sel_i  $end
$var wire      1 X    w1  $end
$var wire      1 Y    w2  $end
$upscope $end


$scope module m1_5 $end
$var wire      1 7    a  $end
$var wire      1 8    b  $end
$var wire      1 >    sel  $end
$var wire      1 B    x  $end
$var wire      1 Q    sel_i  $end
$var wire      1 Z    w1  $end
$var wire      1 [    w2  $end
$upscope $end


$scope module m1_6 $end
$var wire      1 6    a  $end
$var wire      1 7    b  $end
$var wire      1 >    sel  $end
$var wire      1 A    x  $end
$var wire      1 Q    sel_i  $end
$var wire      1 \    w1  $end
$var wire      1 ]    w2  $end
$upscope $end


$scope module m1_7 $end
$var wire      1 5    a  $end
$var wire      1 6    b  $end
$var wire      1 >    sel  $end
$var wire      1 @    x  $end
$var wire      1 Q    sel_i  $end
$var wire      1 ^    w1  $end
$var wire      1 _    w2  $end
$upscope $end


$scope module m1_8 $end
$var wire      1 4    a  $end
$var wire      1 5    b  $end
$var wire      1 >    sel  $end
$var wire      1 ?    x  $end
$var wire      1 Q    sel_i  $end
$var wire      1 `    w1  $end
$var wire      1 a    w2  $end
$upscope $end


$scope module m2_1 $end
$var wire      1 F    a  $end
$var wire      1 P    b  $end
$var wire      1 =    sel  $end
$var wire      1 N    x  $end
$var wire      1 b    sel_i  $end
$var wire      1 c    w1  $end
$var wire      1 d    w2  $end
$upscope $end


$scope module m2_2 $end
$var wire      1 E    a  $end
$var wire      1 P    b  $end
$var wire      1 =    sel  $end
$var wire      1 M    x  $end
$var wire      1 b    sel_i  $end
$var wire      1 e    w1  $end
$var wire      1 d    w2  $end
$upscope $end


$scope module m2_3 $end
$var wire      1 D    a  $end
$var wire      1 F    b  $end
$var wire      1 =    sel  $end
$var wire      1 L    x  $end
$var wire      1 b    sel_i  $end
$var wire      1 f    w1  $end
$var wire      1 g    w2  $end
$upscope $end


$scope module m2_4 $end
$var wire      1 C    a  $end
$var wire      1 E    b  $end
$var wire      1 =    sel  $end
$var wire      1 K    x  $end
$var wire      1 b    sel_i  $end
$var wire      1 h    w1  $end
$var wire      1 i    w2  $end
$upscope $end


$scope module m2_5 $end
$var wire      1 B    a  $end
$var wire      1 D    b  $end
$var wire      1 =    sel  $end
$var wire      1 J    x  $end
$var wire      1 b    sel_i  $end
$var wire      1 j    w1  $end
$var wire      1 k    w2  $end
$upscope $end


$scope module m2_6 $end
$var wire      1 A    a  $end
$var wire      1 C    b  $end
$var wire      1 =    sel  $end
$var wire      1 I    x  $end
$var wire      1 b    sel_i  $end
$var wire      1 l    w1  $end
$var wire      1 m    w2  $end
$upscope $end


$scope module m2_7 $end
$var wire      1 @    a  $end
$var wire      1 B    b  $end
$var wire      1 =    sel  $end
$var wire      1 H    x  $end
$var wire      1 b    sel_i  $end
$var wire      1 n    w1  $end
$var wire      1 o    w2  $end
$upscope $end


$scope module m2_8 $end
$var wire      1 ?    a  $end
$var wire      1 A    b  $end
$var wire      1 =    sel  $end
$var wire      1 G    x  $end
$var wire      1 b    sel_i  $end
$var wire      1 p    w1  $end
$var wire      1 q    w2  $end
$upscope $end


$scope module m4_1 $end
$var wire      1 N    a  $end
$var wire      1 P    b  $end
$var wire      1 <    sel  $end
$var wire      1 )    x  $end
$var wire      1 r    sel_i  $end
$var wire      1 s    w1  $end
$var wire      1 t    w2  $end
$upscope $end


$scope module m4_2 $end
$var wire      1 M    a  $end
$var wire      1 P    b  $end
$var wire      1 <    sel  $end
$var wire      1 (    x  $end
$var wire      1 r    sel_i  $end
$var wire      1 u    w1  $end
$var wire      1 t    w2  $end
$upscope $end


$scope module m4_3 $end
$var wire      1 L    a  $end
$var wire      1 P    b  $end
$var wire      1 <    sel  $end
$var wire      1 '    x  $end
$var wire      1 r    sel_i  $end
$var wire      1 v    w1  $end
$var wire      1 t    w2  $end
$upscope $end


$scope module m4_4 $end
$var wire      1 K    a  $end
$var wire      1 P    b  $end
$var wire      1 <    sel  $end
$var wire      1 &    x  $end
$var wire      1 r    sel_i  $end
$var wire      1 w    w1  $end
$var wire      1 t    w2  $end
$upscope $end


$scope module m4_5 $end
$var wire      1 J    a  $end
$var wire      1 N    b  $end
$var wire      1 <    sel  $end
$var wire      1 %    x  $end
$var wire      1 r    sel_i  $end
$var wire      1 x    w1  $end
$var wire      1 y    w2  $end
$upscope $end


$scope module m4_6 $end
$var wire      1 I    a  $end
$var wire      1 M    b  $end
$var wire      1 <    sel  $end
$var wire      1 $    x  $end
$var wire      1 r    sel_i  $end
$var wire      1 z    w1  $end
$var wire      1 {    w2  $end
$upscope $end


$scope module m4_7 $end
$var wire      1 H    a  $end
$var wire      1 L    b  $end
$var wire      1 <    sel  $end
$var wire      1 #    x  $end
$var wire      1 r    sel_i  $end
$var wire      1 |    w1  $end
$var wire      1 }    w2  $end
$upscope $end


$scope module m4_8 $end
$var wire      1 G    a  $end
$var wire      1 K    b  $end
$var wire      1 <    sel  $end
$var wire      1 "    x  $end
$var wire      1 r    sel_i  $end
$var wire      1 ~    w1  $end
$var wire      1 !!   w2  $end
$upscope $end

$upscope $end

$upscope $end

$enddefinitions $end
$dumpvars
b1000 !
x"
x#
x$
x%
x&
x'
x(
x)
z*
b10101010 +
b0 ,
1-
0.
b0 /
b10 0
b0 1
bx 2
bx 3
14
05
16
07
18
09
1:
0;
0<
0=
0>
x?
x@
xA
xB
xC
xD
xE
xF
xG
xH
xI
xJ
xK
xL
xM
xN
0O
0P
xQ
xR
xS
xT
xU
xV
xW
xX
xY
xZ
x[
x\
x]
x^
x_
x`
xa
xb
xc
xd
xe
xf
xg
xh
xi
xj
xk
xl
xm
xn
xo
xp
xq
xr
xs
xt
xu
xv
xw
xx
xy
xz
x{
x|
x}
x~
x!!
$end
#100
0R
0V
0Z
0^
1Q
0a
0_
0]
0[
0Y
0W
0U
0S
1b
0q
0o
0m
0k
0i
0g
0d
1r
0!!
0}
0{
0y
0t
#200
0F
0D
0B
0@
1`
1\
1X
1T
#300
1E
1C
1A
1?
0n
0j
0f
0c
#350
0-
#400
0N
0L
0J
0H
1p
1l
1h
1e
#500
1M
1K
1I
1G
0|
0x
0v
0s
#600
0)
0'
0%
0#
1~
1z
1w
1u
#700
1(
1&
1$
1"
1-
b1 ,
b100 0
1>
b1 /
b10101010 3
b10101010 2
#800
0Q
1_
1[
1W
#900
1D
1B
1@
0`
0\
0X
0T
#1000
0E
0C
0A
0?
1n
1j
1f
#1050
0-
#1100
1L
1J
1H
0p
0l
0h
0e
#1200
0M
0K
0I
0G
1|
1x
1v
#1300
1'
1%
1#
0~
0z
0w
0u
#1400
0(
0&
0$
0"
1-
b10 ,
b110 0
1=
0>
b10 /
b1010100 3
b1010100 2
#1500
1Q
0_
0[
0W
0b
1o
1k
#1600
0n
0j
0f
0D
0B
0@
1`
1\
1X
1T
#1700
1E
1C
1A
1?
0o
0k
0L
#1750
0-
#1800
0v
0J
0H
1q
1m
1i
#1900
1K
1I
1G
0|
0x
0'
#2000
0%
0#
1~
1z
1w
#2100
1&
1$
1"
1-
b11 ,
b1000 0
1>
b11 /
b10101000 3
b10101000 2
#2200
0Q
1_
1[
1W
#2300
1D
1B
1@
0`
0\
0X
0T
#2400
0E
0C
0A
0?
1o
1k
#2450
0-
#2500
1J
1H
0q
0m
0i
#2600
0K
0I
0G
1|
1x
#2700
1%
1#
0~
0z
0w
#2800
0&
0$
0"
1-
b100 ,
b1010 0
1<
0=
0>
b100 /
b1010000 3
b1010000 2
#2900
1Q
0_
0[
0W
1b
0o
0k
0r
#3000
0|
0x
0J
0H
1n
1j
1f
0D
0B
0@
1`
1\
1X
1T
#3100
1E
1C
1A
1?
0n
0j
0f
0%
0#
#3150
0-
#3200
1p
1l
1h
1e
#3300
1M
1K
1I
1G
#3400
1!!
1{
#3500
1$
1"
1-
b101 ,
b1100 0
1>
b101 /
b10100000 3
b10100000 2
#3600
0Q
1_
1[
1W
#3700
1D
1B
1@
0`
0\
0X
0T
#3800
0E
0C
0A
0?
1n
1j
1f
#3850
0-
#3900
1L
1J
1H
0p
0l
0h
0e
#4000
0M
0K
0I
0G
1}
#4100
1#
0!!
0{
#4200
0$
0"
1-
b110 ,
b1110 0
1=
0>
b110 /
b1000000 3
b1000000 2
#4300
1Q
0_
0[
0W
0b
1o
1k
#4400
0n
0j
0f
0D
0B
0@
1`
1\
1X
1T
#4500
1E
1C
1A
1?
0o
0k
0L
#4550
0-
#4600
0}
0J
0H
1q
1m
1i
#4700
1K
1I
1G
0#
#4800
1!!
#4900
1"
1-
b111 ,
b10000 0
1>
b111 /
b10000000 3
b10000000 2
#5000
0Q
1_
1[
1W
#5100
1D
1B
1@
0`
0\
0X
0T
#5200
0E
0C
0A
0?
1o
1k
#5250
0-
#5300
1J
1H
0q
0m
0i
#5400
0K
0I
0G
#5500
0!!
#5600
0"
1-
b1000 /
b0 3
b0 2
#5950
0-
#6300
1-
b1001 /
1.
bx 2
