HW1-3/2-barrel_shifter/barrel_shifter.v
module barrel_shifter(in, shift, out);
input  [7:0] in;
input  [2:0] shift;
output [7:0] out;

/*Write your code here*/
wire [7:0] x1;
wire [7:0] x2;
reg zero=0;

assign x1[7:0]=shift[0]?{in[6:0],zero}:in[7:0];
assign x2[7:0]=shift[1]?{x1[5:0],zero}:x1[7:0];
assign out[7:0]=shift[2]?{x2[3:0],zero}:x2[7:0];




/*End of code*/
endmodule

HW1-3/2-barrel_shifter/barrel_test.v
`timescale 1ns/10ps
`define CYCLE 8
`define INFILE "Bin.pattern"
`define OUTFILE "Bout_golden.pattern" 

module barrel_test;
parameter pattern_num = 8;
wire [7:0] out;
wire carry;
reg [7:0] x, y;
reg  clk;
reg  stop;
integer i, num, error;

reg [7:0] ans_out;
reg [7:0] barrel_out;

reg [7:0] data_base1 [0:100];
reg [7:0] data_base2 [0:100];

barrel_shifter B (x, y[2:0], out);

initial begin
	$readmemh(`INFILE  , data_base1);
	$readmemh(`OUTFILE , data_base2);
	clk = 1'b1;
	error = 0;
	stop = 0;
	i=0;
end

always begin #(`CYCLE * 0.5) clk = ~clk;
end

initial begin
	x[7:0] = data_base1[0];
	y[7:0] = data_base1[1];
	
	for(num = 2; num < (pattern_num * 2); num = num + 2) begin
		@(posedge clk) begin
			x[7:0] = data_base1[num];
			y[7:0] = data_base1[num + 1];
		end
	end
end


always@(posedge clk) begin
	i <= i + 1;
	if (i >= pattern_num)
		stop <= 1;
end

always@(posedge clk ) begin
	barrel_out <= out;
	ans_out <= data_base2[i];
	if(barrel_out !== ans_out) begin
		error <= error + 1;
		$display("An ERROR occurs at no.%d pattern: Output %b != answer %b.\n", i, barrel_out, ans_out);
	end
end

initial begin
	@(posedge stop) begin
		if(error == 0) begin
			$display("==========================================\n");
			$display("======  Congratulation! You Pass!  =======\n");
			$display("==========================================\n");
		end
		else begin
			$display("===============================\n");
			$display("There are %d errors.", error);
			$display("===============================\n");
		end
		$finish;
	end
end

/*================Dumping Waveform files====================*/
initial begin
$dumpfile("barrel.vcd");
$dumpvars;
/* 	$fsdbDumpfile("barrel.fsdb");
	$fsdbDumpvars;  */
end

endmodule

HW1-3/2-barrel_shifter/barrel.vcd
$date
    Mar 19, 2018  20:24:32
$end
$version
    TOOL:	ncsim	10.20-s114
$end
$timescale
    10 ps
$end

$scope module barrel_test $end
$var parameter 32 !    pattern_num  $end
$var wire      8 "    out [7:0] $end
$var wire      1 #    carry  $end
$var reg       8 $    x [7:0] $end
$var reg       8 %    y [7:0] $end
$var reg       1 &    clk  $end
$var reg       1 '    stop  $end
$var integer  32 (    i  $end
$var integer  32 )    num  $end
$var integer  32 *    error  $end
$var reg       8 +    ans_out [7:0] $end
$var reg       8 ,    barrel_out [7:0] $end

$scope module B $end
$var wire      8 -    in [7:0] $end
$var wire      3 .    shift [2:0] $end
$var wire      8 "    out [7:0] $end
$var wire      8 /    x1 [7:0] $end
$var wire      8 0    x2 [7:0] $end
$var reg       1 1    zero  $end
$upscope $end

$upscope $end

$enddefinitions $end
$dumpvars
b1000 !
b10101010 "
z#
b10101010 $
b0 %
1&
0'
b0 (
b10 )
b0 *
bx +
bx ,
b10101010 -
b0 .
b10101010 /
b10101010 0
01
$end
#1000
0&
#2000
1&
b1 %
b100 )
b1 .
b1010100 /
b1010100 0
b1010100 "
b1 (
b10101010 ,
b10101010 +
#3000
0&
#4000
1&
b10 %
b110 )
b10 .
b10101010 /
b1010000 0
b1010000 "
b10101000 0
b10101000 "
b10 (
b1010100 ,
b1010100 +
#5000
0&
#6000
1&
b11 %
b1000 )
b11 .
b1010100 /
b1010000 0
b1010000 "
b11 (
b10101000 ,
b10101000 +
#7000
0&
#8000
1&
b100 %
b1010 )
b100 .
b10101010 /
b1010100 0
b0 "
b1000000 "
b10101010 0
b10100000 "
b100 (
b1010000 ,
b1010000 +
#9000
0&
#10000
1&
b101 %
b1100 )
b101 .
b1010100 /
b1010100 0
b1000000 "
b101 (
b10100000 ,
b10100000 +
#11000
0&
#12000
1&
b110 %
b1110 )
b110 .
b10101010 /
b1010000 0
b0 "
b10101000 0
b10000000 "
b110 (
b1000000 ,
b1000000 +
#13000
0&
#14000
1&
b111 %
b10000 )
b111 .
b1010100 /
b1010000 0
b0 "
b111 (
b10000000 ,
b10000000 +
#15000
0&
#16000
1&
b1000 (
b0 ,
b0 +
#17000
0&
#18000
1&
b1001 (
1'
bx +
